kaco_ardexa.py
kaco_ardexa-1.0.2.dist-info/METADATA
kaco_ardexa-1.0.2.dist-info/RECORD
kaco_ardexa-1.0.2.dist-info/WHEEL
kaco_ardexa-1.0.2.dist-info/entry_points.txt
kaco_ardexa-1.0.2.dist-info/top_level.txt
