Metadata-Version: 2.1
Name: kaco-ardexa
Version: 1.0.2
Summary: Collect from Kaco Inverters and send the data to your cloud using Ardexa
Home-page: https://github.com/ardexa/kaco-inverters
Author: Ardexa Pty Limited
Author-email: support@ardexa.com
License: UNKNOWN
Project-URL: Bug Reports, https://github.com/ardexa/kaco-inverters/issues
Project-URL: Source, https://github.com/ardexa/kaco-inverters/
Keywords: kaco solar inverter ardexa
Platform: UNKNOWN
Classifier: License :: OSI Approved :: MIT License
Classifier: Programming Language :: Python :: 2
Classifier: Programming Language :: Python :: 2.7
Classifier: Programming Language :: Python :: 3
Classifier: Programming Language :: Python :: 3.4
Classifier: Programming Language :: Python :: 3.5
Classifier: Programming Language :: Python :: 3.6
Requires-Python: >=2.7
Requires-Dist: future
Requires-Dist: ardexaplugin
Requires-Dist: Click
Requires-Dist: pyserial
